django_randomslugfield-0.3.0.post1.dist-info/licenses/LICENSE
randomslugfield/__init__.py
randomslugfield/fields.py
randomslugfield/models.py
randomslugfield/tests.py
django_randomslugfield-0.3.0.post1.dist-info/METADATA
django_randomslugfield-0.3.0.post1.dist-info/WHEEL
django_randomslugfield-0.3.0.post1.dist-info/top_level.txt
django_randomslugfield-0.3.0.post1.dist-info/RECORD
