Metadata-Version: 2.4
Name: django-randomslugfield
Version: 0.3.0.post1
Summary: A Django field that automatically generates random slugs.
License-Expression: MIT
Project-URL: Source, http://github.com/mkrjhnsn/django-randomslugfield
Classifier: Development Status :: 7 - Inactive
Classifier: Environment :: Web Environment
Classifier: Framework :: Django
Classifier: Intended Audience :: Developers
Classifier: Operating System :: OS Independent
Classifier: Programming Language :: Python
Classifier: Programming Language :: Python :: 2.7
Classifier: Programming Language :: Python :: 3.3
Classifier: Programming Language :: Python :: 3.4
License-File: LICENSE
Dynamic: license-file
